qlauncher/__init__.py
qlauncher/exceptions.py
qlauncher/utils.py
qlauncher/base/__init__.py
qlauncher/base/adapter_structure.py
qlauncher/base/base.py
qlauncher/base/translator.py
qlauncher/hampy/__init__.py
qlauncher/hampy/debug.py
qlauncher/hampy/equations.py
qlauncher/hampy/object.py
qlauncher/hampy/utils.py
qlauncher/launcher/__init__.py
qlauncher/launcher/profiling_launcher.py
qlauncher/launcher/qlauncher.py
qlauncher/launcher/aql/__init__.py
qlauncher/launcher/aql/aql.py
qlauncher/launcher/aql/aql_task.py
qlauncher/problems/__init__.py
qlauncher/problems/problem_formulations/__init__.py
qlauncher/problems/problem_formulations/bqm.py
qlauncher/problems/problem_formulations/hamiltonian.py
qlauncher/problems/problem_formulations/other.py
qlauncher/problems/problem_formulations/qubo.py
qlauncher/problems/problem_formulations/hamiltonians/__init__.py
qlauncher/problems/problem_formulations/hamiltonians/tsp.py
qlauncher/problems/problem_formulations/jssp/Binary.py
qlauncher/problems/problem_formulations/jssp/__init__.py
qlauncher/problems/problem_formulations/jssp/pyqubo_scheduler.py
qlauncher/problems/problem_formulations/jssp/qiskit_scheduler.py
qlauncher/problems/problem_formulations/jssp/scheduler.py
qlauncher/problems/problem_initialization/__init__.py
qlauncher/problems/problem_initialization/ec.py
qlauncher/problems/problem_initialization/graph_coloring.py
qlauncher/problems/problem_initialization/jssp.py
qlauncher/problems/problem_initialization/maxcut.py
qlauncher/problems/problem_initialization/molecule.py
qlauncher/problems/problem_initialization/qatm.py
qlauncher/problems/problem_initialization/raw.py
qlauncher/problems/problem_initialization/tabular_ml.py
qlauncher/problems/problem_initialization/tsp.py
qlauncher/routines/__init__.py
qlauncher/routines/cirq.py
qlauncher/routines/dwave/__init__.py
qlauncher/routines/dwave/algorithms.py
qlauncher/routines/dwave/backends.py
qlauncher/routines/orca/__init__.py
qlauncher/routines/orca/algorithms.py
qlauncher-2.0.6.dist-info/licenses/LICENSE
qlauncher-2.0.6.dist-info/METADATA
qlauncher-2.0.6.dist-info/WHEEL
qlauncher-2.0.6.dist-info/top_level.txt
qlauncher-2.0.6.dist-info/RECORD
